pyinstrument_decorator/__init__.py
pyinstrument_decorator/profile.py
pyinstrument_decorator-0.1.3.dist-info/METADATA
pyinstrument_decorator-0.1.3.dist-info/WHEEL
pyinstrument_decorator-0.1.3.dist-info/top_level.txt
pyinstrument_decorator-0.1.3.dist-info/RECORD
