Metadata-Version: 2.1
Name: pyinstrument-decorator
Version: 0.1.3
Summary: Provides the `profile` context manager/decorator
Home-page: UNKNOWN
Author: Bao Wei
Author-email: baowei.ur521@gmail.com
License: MIT
Platform: UNKNOWN
Requires-Python: >=3.7
Requires-Dist: atomic-write-path (>=1.3)
Requires-Dist: functional-itertools (>=0.9)
Requires-Dist: pyinstrument (>=3.1)
